hookio/__init__.py
hookio/hookio.py
hookio/hookio_old.py
hookio-0.0.8.dist-info/METADATA
hookio-0.0.8.dist-info/WHEEL
hookio-0.0.8.dist-info/top_level.txt
hookio-0.0.8.dist-info/RECORD
